django_hunger-2.1.1.dist-info/DESCRIPTION.rst
django_hunger-2.1.1.dist-info/METADATA
django_hunger-2.1.1.dist-info/RECORD
django_hunger-2.1.1.dist-info/metadata.json
django_hunger-2.1.1.dist-info/WHEEL
django_hunger-2.1.1.dist-info/top_level.txt
hunger/models.py
hunger/urls.py
hunger/utils.py
hunger/views.py
hunger/__init__.py
hunger/forms.py
hunger/email.py
hunger/admin.py
hunger/middleware.py
hunger/templates/hunger/invite_email.txt
hunger/templates/hunger/beta_confirm.txt
hunger/templates/hunger/invalid.html
hunger/templates/hunger/beta_confirm.html
hunger/templates/hunger/invite_email_subject.txt
hunger/templates/hunger/beta_confirm.email
hunger/templates/hunger/invite_email.email
hunger/templates/hunger/invite_email.html
