Metadata-Version: 2.0
Name: django-hunger
Version: 2.1.1
Summary: A Django app to manage a private beta phase.
Home-page: https://github.com/joshuakarjala/django-hunger/
Author: Joshua Karjala-Svenden
Author-email: joshua@fluxuries.com
License: MIT
Platform: any
Classifier: Development Status :: 5 - Production/Stable
Classifier: Intended Audience :: Developers
Classifier: License :: OSI Approved :: MIT License
Classifier: Operating System :: OS Independent
Classifier: Programming Language :: Python
Classifier: Topic :: Software Development :: Libraries :: Python Modules
Classifier: Framework :: Django
Provides-Extra: test
Requires-Dist: Django (>=1.3); extra == 'test'
